fafig-1.0.9.dist-info/top_level.txt
fafig-1.0.9.dist-info/RECORD
fafig-1.0.9.dist-info/METADATA
fafig-1.0.9.dist-info/WHEEL
fafig/fam.cpython-311-x86_64-linux-gnu.so
