Metadata-Version: 2.1
Name: fafig
Version: 1.0.9
Summary: Fafig Studio add-ons manager for Blender
Author: Fafig Studio
Requires-Python: >=3.10,<3.12
